PathlibIO/Handler.py
PathlibIO/__init__.py
PathlibIO/exit_code_tests.py
PathlibIO/not_implemented.py
PathlibIO/properties_etc.py
PathlibIO-1.0.0.dist-info/LICENSE
PathlibIO-1.0.0.dist-info/METADATA
PathlibIO-1.0.0.dist-info/WHEEL
PathlibIO-1.0.0.dist-info/entry_points.txt
PathlibIO-1.0.0.dist-info/top_level.txt
PathlibIO-1.0.0.dist-info/RECORD
