Metadata-Version: 2.1
Name: PathlibIO
Version: 1.0.0
Summary: CLI functionality of Python's Pathlib module
License: GNU GENERAL PUBLIC LICENSE
Project-URL: Homepage, https://github.com/jb2170/PathlibIO/
License-File: LICENSE
